[
  {
    "itemName" : "Population Program Worker II",
    "itemNo" : "973",
    "sg" : "SG7",
    "summary" : "No description provided",
    "education" : [
      "Completion of two years studies in College"
    ],
    "eligibility" : [ 
      {
        "id" : "cs-subprof",
        "name" : "CS Sub-professional (1st Level Eligibility)"
      }
    ],
    "experience" : [
      "None required"
    ],
    "training" : [
      "None required"
    ],
    "competencies" : [
      {
        "id" : "ORGNL-INTGRITY-2017",
        "name" : "Integrity"
      },
      {
        "id" : "ORGNL-SRVORNTD-2017",
        "name" : "Customer and Service Orientedness"
      },
      {
        "id" : "ORGNL-PRFSNLSM-2017",
        "name" : "Professionalism"
      },
      {
        "id" : "ORGNL-EFTVDEVT-2017",
        "name" : "Effective and Continuous Development"
      },
      {
        "id" : "ORGNL-PSOLVING-2017",
        "name" : "Problem-solving and Decision-making"
      },
      {
        "id" : "ORGNL-EFFCOMMT-2017",
        "name" : "Effective Communication"
      },
      {
        "id" : "ORGNL-ADPTFLEX-2017",
        "name" : "Adaptability and Flexibility"
      }
    ]
  }
]
